{
  "prepare_queue": {
    "installed": [],
    "uninstalled": []
  },
  "config_munge": {
    "files": {}
  },
  "installed_plugins": {
    "cordova-plugin-whitelist": {
      "PACKAGE_NAME": "com.fydp.streamingOS.LoginApp"
    },
    "cordova-plugin-keyboard": {
      "PACKAGE_NAME": "com.fydp.streamingOS.LoginApp"
    }
  },
  "dependent_plugins": {},
  "modules": [
    {
      "file": "plugins/cordova-plugin-keyboard/www/keyboard.js",
      "id": "cordova-plugin-keyboard.keyboard",
      "pluginId": "cordova-plugin-keyboard",
      "clobbers": [
        "window.Keyboard"
      ]
    }
  ],
  "plugin_metadata": {
    "cordova-plugin-whitelist": "1.3.4",
    "cordova-plugin-keyboard": "1.2.0"
  }
}
